{"nodes": [{"id": "chills"}, {"id": "fatigue"}, {"id": "cough"}, {"id": "high fever"}, {"id": "breathlessness"}, {"id": "sweating"}, {"id": "malaise"}, {"id": "phlegm"}, {"id": "chest pain"}, {"id": "fast heart rate"}, {"id": "rusty sputum"}, {"id": "Pneumonia"}], "links": [{"source": "Pneumonia", "target": "chills"}, {"source": "Pneumonia", "target": "fatigue"}, {"source": "Pneumonia", "target": "cough"}, {"source": "Pneumonia", "target": "high fever"}, {"source": "Pneumonia", "target": "breathlessness"}, {"source": "Pneumonia", "target": "sweating"}, {"source": "Pneumonia", "target": "malaise"}, {"source": "Pneumonia", "target": "phlegm"}, {"source": "Pneumonia", "target": "chest pain"}, {"source": "Pneumonia", "target": "fast heart rate"}, {"source": "Pneumonia", "target": "rusty sputum"}]}